setup.py
pypro/__init__.py
pypro/head_builder.py
pypro/utils.py
pypro/snmp/__init__.py
pypro/snmp/config.py
pypro/snmp/example.py
pypro/snmp/example_me.py
pypro/snmp/main.py
pypro/snmp/pypro_snmp.avsc
pypro/snmp/pypro_snmp_float.avsc
pypro/snmp/pypro_snmp_int.avsc
pypro/snmp/pypro_snmp_str.avsc
pypro/snmp/snmp_poller.py
pypro/snmp/loggers/__init__.py
pypro/snmp/loggers/csv_logger.py
pypro/snmp/loggers/es_file_logger.py
pypro/snmp/loggers/es_network_logger.py
pypro/snmp/loggers/influx_logger.py
pypro/snmp/loggers/kafka_avro_logger.py
pypro/snmp/loggers/kafka_json_logger.py
pypro/snmp/oids/__init__.py
pypro/snmp/oids/cpu_load_prct.py
pypro/snmp/oids/oid.py
pypro/snmp/oids/ram_used.py
pypro/snmp/oids/simple.py
pypro_snmp.egg-info/PKG-INFO
pypro_snmp.egg-info/SOURCES.txt
pypro_snmp.egg-info/dependency_links.txt
pypro_snmp.egg-info/requires.txt
pypro_snmp.egg-info/top_level.txt
pypro_snmp.egg-info/zip-safe